<?xml version="1.0" encoding="UTF-8" ?>
<templates xml:space="preserve">
    <t t-name="iboard.Title" owl="1">
        <div t-attf-class="indicator-card indicator-card-theme-{{ props.chart.palette}}">
            <div class="indicator-body">
                  <h4 class="indicator-card-title">
                      <t t-esc="props.chart.title"/>
                  </h4>
                <div class="indicator-card-number">
                    <t t-esc="data.total"/>
                </div>
            </div>
            <t t-call="iboard.titleBackGround"/>
     </div>

    </t>
    <t t-name="iboard.titleBackGround" owl="1">
      <svg xmlns="http://www.w3.org/2000/svg" viewBox="0 0 1440 320">
          <t t-if="props.chart.title_design=='d1' ">
                <path
                        t-att-fill="colors"
                        fill-opacity="1"
                        d="M0,0L21.8,26.7C43.6,53,87,107,131,122.7C174.5,139,218,117,262,106.7C305.5,96,349,96,393,117.3C436.4,139,480,181,524,186.7C567.3,192,611,160,655,122.7C698.2,85,742,43,785,48C829.1,53,873,107,916,138.7C960,171,1004,181,1047,202.7C1090.9,224,1135,256,1178,224C1221.8,192,1265,96,1309,85.3C1352.7,75,1396,149,1418,186.7L1440,224L1440,320L1418.2,320C1396.4,320,1353,320,1309,320C1265.5,320,1222,320,1178,320C1134.5,320,1091,320,1047,320C1003.6,320,960,320,916,320C872.7,320,829,320,785,320C741.8,320,698,320,655,320C610.9,320,567,320,524,320C480,320,436,320,393,320C349.1,320,305,320,262,320C218.2,320,175,320,131,320C87.3,320,44,320,22,320L0,320Z"/>
          </t>
          <t t-if="props.chart.title_design=='d2' ">
             <path
                     t-att-fill="colors"
                     fill-opacity="1"
                     d="M0,64L60,69.3C120,75,240,85,360,122.7C480,160,600,224,720,224C840,224,960,160,1080,112C1200,64,1320,32,1380,16L1440,0L1440,320L1380,320C1320,320,1200,320,1080,320C960,320,840,320,720,320C600,320,480,320,360,320C240,320,120,320,60,320L0,320Z"/>
          </t>
          <t t-if="props.chart.title_design=='d3' ">
           <path t-att-fill="colors"
                 fill-opacity="1"
                 d="M0,0L21.8,53.3C43.6,107,87,213,131,261.3C174.5,309,218,299,262,272C305.5,245,349,203,393,197.3C436.4,192,480,224,524,213.3C567.3,203,611,149,655,160C698.2,171,742,245,785,250.7C829.1,256,873,192,916,165.3C960,139,1004,149,1047,133.3C1090.9,117,1135,75,1178,96C1221.8,117,1265,203,1309,234.7C1352.7,267,1396,245,1418,234.7L1440,224L1440,320L1418.2,320C1396.4,320,1353,320,1309,320C1265.5,320,1222,320,1178,320C1134.5,320,1091,320,1047,320C1003.6,320,960,320,916,320C872.7,320,829,320,785,320C741.8,320,698,320,655,320C610.9,320,567,320,524,320C480,320,436,320,393,320C349.1,320,305,320,262,320C218.2,320,175,320,131,320C87.3,320,44,320,22,320L0,320Z"></path>
          </t>
      </svg>
    </t>
</templates>